fathom_pdf/__about__.py
fathom_pdf/__init__.py
fathom_pdf-0.0.1.dist-info/METADATA
fathom_pdf-0.0.1.dist-info/WHEEL
fathom_pdf-0.0.1.dist-info/licenses/LICENSE.txt
fathom_pdf-0.0.1.dist-info/RECORD
