Metadata-Version: 2.4
Name: fathom-pdf
Version: 0.0.1
Project-URL: Documentation, https://github.com/arunksoman/fathom-pdf#readme
Project-URL: Issues, https://github.com/arunksoman/fathom-pdf/issues
Project-URL: Source, https://github.com/arunksoman/fathom-pdf
Author-email: arunksoman <arunksoman69@gmail.com>
License-Expression: MIT
License-File: LICENSE.txt
Classifier: Development Status :: 4 - Beta
Classifier: Programming Language :: Python
Classifier: Programming Language :: Python :: 3.8
Classifier: Programming Language :: Python :: 3.9
Classifier: Programming Language :: Python :: 3.10
Classifier: Programming Language :: Python :: 3.11
Classifier: Programming Language :: Python :: 3.12
Classifier: Programming Language :: Python :: Implementation :: CPython
Classifier: Programming Language :: Python :: Implementation :: PyPy
Requires-Python: >=3.8
